penelopa/__init__.py
penelopa/ai.py
penelopa/configuration.py
penelopa/penelopa.py
penelopa/penelopa_wrapper.py
tests/__init__.py
penelopa-0.0.30.dist-info/METADATA
penelopa-0.0.30.dist-info/WHEEL
penelopa-0.0.30.dist-info/entry_points.txt
penelopa-0.0.30.dist-info/top_level.txt
penelopa-0.0.30.dist-info/RECORD
