Metadata-Version: 2.1
Name: penelopa
Version: 0.0.30
Summary: Penelopa: AI-driven codebase modifier using OpenAI GPT models
Home-page: https://github.com/chigwell/penelopa
Author: Eugene Evstafev
Author-email: chigwel@gmail.com
License: UNKNOWN
Platform: UNKNOWN
Requires-Python: >=3.6
Requires-Dist: pathspec
Requires-Dist: argparse
Requires-Dist: pyyaml
Requires-Dist: openai
Requires-Dist: penelopa-dialog
Requires-Dist: ProjectCodebaseToJsonl
Requires-Dist: clarifyquestgen
Requires-Dist: CodebaseLister
Requires-Dist: mistralai
